Workbook

Sheet Assumptions
A1: HypeTest MRR Model - Assumptions
A3: PRICING
A4: Starter price ($/mo) | B4: 49
A5: Pro price ($/mo) | B5: 149
A6: Team price ($/mo) | B6: 349
A8: API COSTS
A9: Cost per research run ($) | B9: 0.05
A10: Runs included - Starter | B10: 30
A11: Runs included - Pro | B11: 100
A12: Runs included - Team | B12: 500
A14: GROWTH ASSUMPTIONS
A15: Month 1 free signups | B15: 200
A16: Monthly signup growth rate | B16: 0.15
A17: Free-to-Starter conversion rate | B17: 0.04
A18: Free-to-Pro conversion rate | B18: 0.02
A19: Team accounts acquired (month 6+) | B19: 1
A21: CHURN & EXPANSION
A22: Monthly churn rate (Starter) | B22: 0.08
A23: Monthly churn rate (Pro) | B23: 0.05
A24: Monthly churn rate (Team) | B24: 0.03
A25: Starter-to-Pro upgrade rate (monthly) | B25: 0.05

Sheet Monthly Projection
A1: HypeTest 12-Month MRR Projection
B3: Month 1 | C3: Month 2 | D3: Month 3 | E3: Month 4 | F3: Month 5 | G3: Month 6 | H3: Month 7 | I3: Month 8 | J3: Month 9 | K3: Month 10 | L3: Month 11 | M3: Month 12
A4: FREE SIGNUPS
A5: New free signups | B5: =Assumptions!B15 -> 200 | C5: =B5*(1+Assumptions!B16) -> 230 | D5: =C5*(1+Assumptions!B16) -> 264.5 | E5: =D5*(1+Assumptions!B16) -> 304.175 | F5: =E5*(1+Assumptions!B16) -> 349.80125 | G5: =F5*(1+Assumptions!B16) -> 402.27144 | H5: =G5*(1+Assumptions!B16) -> 462.61215 | I5: =H5*(1+Assumptions!B16) -> 532.00398 | J5: =I5*(1+Assumptions!B16) -> 611.80457 | K5: =J5*(1+Assumptions!B16) -> 703.57526 | L5: =K5*(1+Assumptions!B16) -> 809.11155 | M5: =L5*(1+Assumptions!B16) -> 930.47828
A6: Cumulative free users | B6: =B5 -> 200 | C6: =B6+C5 -> 430 | D6: =C6+D5 -> 694.5 | E6: =D6+E5 -> 998.675 | F6: =E6+F5 -> 1348.4762 | G6: =F6+G5 -> 1750.7477 | H6: =G6+H5 -> 2213.3598 | I6: =H6+I5 -> 2745.3638 | J6: =I6+J5 -> 3357.1684 | ... M6: =L6+M5 -> 5800.3335
A8: CONVERSIONS
A9: New Starter conversions | B9: =ROUND(B5*Assumptions!B17,0) -> 8 | C9: =ROUND(C5*Assumptions!B17,0) -> 9 | D9: =ROUND(D5*Assumptions!B17,0) -> 11 | E9: =ROUND(E5*Assumptions!B17,0) -> 12 | F9: =ROUND(F5*Assumptions!B17,0) -> 14 | G9: =ROUND(G5*Assumptions!B17,0) -> 16 | H9: =ROUND(H5*Assumptions!B17,0) -> 19 | I9: =ROUND(I5*Assumptions!B17,0) -> 21 | J9: =ROUND(J5*Assumptions!B17,0) -> 24 | K9: =ROUND(K5*Assumptions!B17,0) -> 28 | L9: =ROUND(L5*Assumptions!B17,0) -> 32 | M9: =ROUND(M5*Assumptions!B17,0) -> 37
A10: New Pro conversions | B10: =ROUND(B5*Assumptions!B18,0) -> 4 | C10: =ROUND(C5*Assumptions!B18,0) -> 5 | D10: =ROUND(D5*Assumptions!B18,0) -> 5 | E10: =ROUND(E5*Assumptions!B18,0) -> 6 | F10: =ROUND(F5*Assumptions!B18,0) -> 7 | G10: =ROUND(G5*Assumptions!B18,0) -> 8 | H10: =ROUND(H5*Assumptions!B18,0) -> 9 | I10: =ROUND(I5*Assumptions!B18,0) -> 11 | J10: =ROUND(J5*Assumptions!B18,0) -> 12 | K10: =ROUND(K5*Assumptions!B18,0) -> 14 | L10: =ROUND(L5*Assumptions!B18,0) -> 16 | M10: =ROUND(M5*Assumptions!B18,0) -> 19
A11: Starter-to-Pro upgrades | B11: 0 | C11: =ROUND(B15*Assumptions!B25,0) -> 0 | D11: =ROUND(C15*Assumptions!B25,0) -> 1 | E11: =ROUND(D15*Assumptions!B25,0) -> 1 | F11: =ROUND(E15*Assumptions!B25,0) -> 2 | G11: =ROUND(F15*Assumptions!B25,0) -> 2 | H11: =ROUND(G15*Assumptions!B25,0) -> 3 | I11: =ROUND(H15*Assumptions!B25,0) -> 3 | J11: =ROUND(I15*Assumptions!B25,0) -> 4 | K11: =ROUND(J15*Assumptions!B25,0) -> 5 | L11: =ROUND(K15*Assumptions!B25,0) -> 5 | M11: =ROUND(L15*Assumptions!B25,0) -> 6
A13: ACTIVE PAYING CUSTOMERS
A14: Starter churned | B14: 0 | C14: =ROUND(B15*Assumptions!B22,0) -> 1 | D14: =ROUND(C15*Assumptions!B22,0) -> 1 | E14: =ROUND(D15*Assumptions!B22,0) -> 2 | F14: =ROUND(E15*Assumptions!B22,0) -> 3 | G14: =ROUND(F15*Assumptions!B22,0) -> 3 | H14: =ROUND(G15*Assumptions!B22,0) -> 4 | I14: =ROUND(H15*Assumptions!B22,0) -> 5 | J14: =ROUND(I15*Assumptions!B22,0) -> 6 | K14: =ROUND(J15*Assumptions!B22,0) -> 7 | L14: =ROUND(K15*Assumptions!B22,0) -> 9 | M14: =ROUND(L15*Assumptions!B22,0) -> 10
A15: Active Starter customers | B15: =B9 -> 8 | C15: =B15+C9-C14-C11 -> 16 | D15: =C15+D9-D14-D11 -> 25 | E15: =D15+E9-E14-E11 -> 34 | F15: =E15+F9-F14-F11 -> 43 | G15: =F15+G9-G14-G11 -> 54 | H15: =G15+H9-H14-H11 -> 66 | I15: =H15+I9-I14-I11 -> 79 | J15: =I15+J9-J14-J11 -> 93 | ... M15: =L15+M9-M14-M11 -> 148
A16: Pro churned | B16: 0 | C16: =ROUND(B17*Assumptions!B23,0) -> 0 | D16: =ROUND(C17*Assumptions!B23,0) -> 0 | E16: =ROUND(D17*Assumptions!B23,0) -> 1 | F16: =ROUND(E17*Assumptions!B23,0) -> 1 | G16: =ROUND(F17*Assumptions!B23,0) -> 1 | H16: =ROUND(G17*Assumptions!B23,0) -> 2 | I16: =ROUND(H17*Assumptions!B23,0) -> 2 | J16: =ROUND(I17*Assumptions!B23,0) -> 3 | K16: =ROUND(J17*Assumptions!B23,0) -> 4 | L16: =ROUND(K17*Assumptions!B23,0) -> 4 | M16: =ROUND(L17*Assumptions!B23,0) -> 5
A17: Active Pro customers | B17: =B10 -> 4 | C17: =B17+C10+C11-C16 -> 9 | D17: =C17+D10+D11-D16 -> 15 | E17: =D17+E10+E11-E16 -> 21 | F17: =E17+F10+F11-F16 -> 29 | G17: =F17+G10+G11-G16 -> 38 | H17: =G17+H10+H11-H16 -> 48 | I17: =H17+I10+I11-I16 -> 60 | J17: =I17+J10+J11-J16 -> 73 | ... M17: =L17+M10+M11-M16 -> 125
A18: Active Team customers | B18: 0 | C18: 0 | D18: 0 | E18: 0 | F18: 0 | G18: =MAX(0,ROUND(F18*(1-Assumptions!B24),0)+Assumptions!B19) -> 1 | H18: =MAX(0,ROUND(G18*(1-Assumptions!B24),0)+Assumptions!B19) -> 2 | I18: =MAX(0,ROUND(H18*(1-Assumptions!B24),0)+Assumptions!B19) -> 3 | J18: =MAX(0,ROUND(I18*(1-Assumptions!B24),0)+Assumptions!B19) -> 4 | K18: =MAX(0,ROUND(J18*(1-Assumptions!B24),0)+Assumptions!B19) -> 5 | L18: =MAX(0,ROUND(K18*(1-Assumptions!B24),0)+Assumptions!B19) -> 6 | M18: =MAX(0,ROUND(L18*(1-Assumptions!B24),0)+Assumptions!B19) -> 7
A19: Total paying customers | B19: =B15+B17+B18 -> 12 | C19: =C15+C17+C18 -> 25 | D19: =D15+D17+D18 -> 40 | E19: =E15+E17+E18 -> 55 | F19: =F15+F17+F18 -> 72 | G19: =G15+G17+G18 -> 93 | H19: =H15+H17+H18 -> 116 | I19: =I15+I17+I18 -> 142 | ... M19: =M15+M17+M18 -> 280
A21: MONTHLY RECURRING REVENUE
A22: Starter MRR | B22: =B15*Assumptions!B4 -> 392 | C22: =C15*Assumptions!B4 -> 784 | D22: =D15*Assumptions!B4 -> 1225 | E22: =E15*Assumptions!B4 -> 1666 | F22: =F15*Assumptions!B4 -> 2107 | G22: =G15*Assumptions!B4 -> 2646 | H22: =H15*Assumptions!B4 -> 3234 | I22: =I15*Assumptions!B4 -> 3871 | J22: =J15*Assumptions!B4 -> 4557 | K22: =K15*Assumptions!B4 -> 5341 | L22: =L15*Assumptions!B4 -> 6223 | M22: =M15*Assumptions!B4 -> 7252
A23: Pro MRR | B23: =B17*Assumptions!B5 -> 596 | C23: =C17*Assumptions!B5 -> 1341 | D23: =D17*Assumptions!B5 -> 2235 | E23: =E17*Assumptions!B5 -> 3129 | F23: =F17*Assumptions!B5 -> 4321 | G23: =G17*Assumptions!B5 -> 5662 | H23: =H17*Assumptions!B5 -> 7152 | I23: =I17*Assumptions!B5 -> 8940 | J23: =J17*Assumptions!B5 -> 10877 | K23: =K17*Assumptions!B5 -> 13112 | L23: =L17*Assumptions!B5 -> 15645 | M23: =M17*Assumptions!B5 -> 18625
A24: Team MRR | B24: =B18*Assumptions!B6 -> 0 | C24: =C18*Assumptions!B6 -> 0 | D24: =D18*Assumptions!B6 -> 0 | E24: =E18*Assumptions!B6 -> 0 | F24: =F18*Assumptions!B6 -> 0 | G24: =G18*Assumptions!B6 -> 349 | H24: =H18*Assumptions!B6 -> 698 | I24: =I18*Assumptions!B6 -> 1047 | J24: =J18*Assumptions!B6 -> 1396 | K24: =K18*Assumptions!B6 -> 1745 | L24: =L18*Assumptions!B6 -> 2094 | M24: =M18*Assumptions!B6 -> 2443
A25: Total MRR | B25: =B22+B23+B24 -> 988 | C25: =C22+C23+C24 -> 2125 | D25: =D22+D23+D24 -> 3460 | E25: =E22+E23+E24 -> 4795 | F25: =F22+F23+F24 -> 6428 | G25: =G22+G23+G24 -> 8657 | H25: =H22+H23+H24 -> 11084 | I25: =I22+I23+I24 -> 13858 | ... M25: =M22+M23+M24 -> 28320
A27: UNIT ECONOMICS
A28: Estimated API cost | B28: =(B15*Assumptions!B10+B17*Assumptions!B11+B18*Assumptions!B12+B5*3)*Assumptions!B9 -> 62 | C28: =(C15*Assumptions!B10+C17*Assumptions!B11+C18*Assumptions!B12+C5*3)*Assumptions!B9 -> 103.5 | D28: =(D15*Assumptions!B10+D17*Assumptions!B11+D18*Assumptions!B12+D5*3)*Assumptions!B9 -> 152.175 | E28: =(E15*Assumptions!B10+E17*Assumptions!B11+E18*Assumptions!B12+E5*3)*Assumptions!B9 -> 201.62625 | F28: =(F15*Assumptions!B10+F17*Assumptions!B11+F18*Assumptions!B12+F5*3)*Assumptions!B9 -> 261.97019 | G28: =(G15*Assumptions!B10+G17*Assumptions!B11+G18*Assumptions!B12+G5*3)*Assumptions!B9 -> 356.34072 | H28: =(H15*Assumptions!B10+H17*Assumptions!B11+H18*Assumptions!B12+H5*3)*Assumptions!B9 -> 458.39182 | I28: =(I15*Assumptions!B10+I17*Assumptions!B11+I18*Assumptions!B12+I5*3)*Assumptions!B9 -> 573.3006 | J28: =(J15*Assumptions!B10+J17*Assumptions!B11+J18*Assumptions!B12+J5*3)*Assumptions!B9 -> 696.27069 | K28: =(K15*Assumptions!B10+K17*Assumptions!B11+K18*Assumptions!B12+K5*3)*Assumptions!B9 -> 834.03629 | L28: =(L15*Assumptions!B10+L17*Assumptions!B11+L18*Assumptions!B12+L5*3)*Assumptions!B9 -> 986.86673 | M28: =(M15*Assumptions!B10+M17*Assumptions!B11+M18*Assumptions!B12+M5*3)*Assumptions!B9 -> 1161.5717
A29: Gross profit | B29: =B25-B28 -> 926 | C29: =C25-C28 -> 2021.5 | D29: =D25-D28 -> 3307.825 | E29: =E25-E28 -> 4593.3737 | F29: =F25-F28 -> 6166.0298 | G29: =G25-G28 -> 8300.6593 | H29: =H25-H28 -> 10625.608 | I29: =I25-I28 -> 13284.699 | ... M29: =M25-M28 -> 27158.428
A30: Gross margin | B30: =IF(B25>0,B29/B25,0) -> 0.93724696 | C30: =IF(C25>0,C29/C25,0) -> 0.95129412 | D30: =IF(D25>0,D29/D25,0) -> 0.95601879 | E30: =IF(E25>0,E29/E25,0) -> 0.95795073 | F30: =IF(F25>0,F29/F25,0) -> 0.95924546 | G30: =IF(G25>0,G29/G25,0) -> 0.95883785 | H30: =IF(H25>0,H29/H25,0) -> 0.95864383 | I30: =IF(I25>0,I29/I25,0) -> 0.95863035 | ... M30: =IF(M25>0,M29/M25,0) -> 0.95898405
A31: ARPU (blended) | B31: =IF(B19>0,B25/B19,0) -> 82.333333 | C31: =IF(C19>0,C25/C19,0) -> 85 | D31: =IF(D19>0,D25/D19,0) -> 86.5 | E31: =IF(E19>0,E25/E19,0) -> 87.181818 | F31: =IF(F19>0,F25/F19,0) -> 89.277778 | G31: =IF(G19>0,G25/G19,0) -> 93.086022 | H31: =IF(H19>0,H25/H19,0) -> 95.551724 | I31: =IF(I19>0,I25/I19,0) -> 97.591549 | ... M31: =IF(M19>0,M25/M19,0) -> 101.14286
A33: CUMULATIVE
A34: Cumulative revenue | B34: =B25 -> 988 | C34: =B34+C25 -> 3113 | D34: =C34+D25 -> 6573 | E34: =D34+E25 -> 11368 | F34: =E34+F25 -> 17796 | G34: =F34+G25 -> 26453 | H34: =G34+H25 -> 37537 | I34: =H34+I25 -> 51395 | J34: =I34+J25 -> 68225 | ... M34: =L34+M25 -> 140705
A35: Cumulative API cost | B35: =B28 -> 62 | C35: =B35+C28 -> 165.5 | D35: =C35+D28 -> 317.675 | E35: =D35+E28 -> 519.30125 | F35: =E35+F28 -> 781.27144 | G35: =F35+G28 -> 1137.6122 | H35: =G35+H28 -> 1596.004 | I35: =H35+I28 -> 2169.3046 | J35: =I35+J28 -> 2865.5753 | ... M35: =L35+M28 -> 5848.05
A36: Cumulative gross profit | B36: =B29 -> 926 | C36: =B36+C29 -> 2947.5 | D36: =C36+D29 -> 6255.325 | E36: =D36+E29 -> 10848.699 | F36: =E36+F29 -> 17014.729 | G36: =F36+G29 -> 25315.388 | H36: =G36+H29 -> 35940.996 | I36: =H36+I29 -> 49225.695 | J36: =I36+J29 -> 65359.425 | ... M36: =L36+M29 -> 134856.95
A38: ARR (MRR x 12) | B38: =B25*12 -> 11856 | C38: =C25*12 -> 25500 | D38: =D25*12 -> 41520 | E38: =E25*12 -> 57540 | F38: =F25*12 -> 77136 | G38: =G25*12 -> 103884 | H38: =H25*12 -> 133008 | I38: =I25*12 -> 166296 | ... M38: =M25*12 -> 339840
A40: Notes:
A41: 1. All blue values on Assumptions tab are editable inputs.
A42: 2. Model assumes organic growth only (no paid acquisition).
A43: 3. Team accounts start acquiring from month 6 (sales cycle).
A44: 4. Churn is applied to previous month's base before adding new.
A45: 5. Free users assumed to use ~3 runs/month for API cost calc.
A46: 6. Does not include Vercel, Supabase, or domain costs (~$50-100/mo fixed).
